Sastrawi/__init__.py
Sastrawi/Dictionary/ArrayDictionary.py
Sastrawi/Dictionary/DictionaryInterface.py
Sastrawi/Dictionary/__init__.py
Sastrawi/Morphology/InvalidAffixPairSpecification.py
Sastrawi/Morphology/__init__.py
Sastrawi/Morphology/Disambiguator/DisambiguatorPrefixRule1.py
Sastrawi/Morphology/Disambiguator/DisambiguatorPrefixRule10.py
Sastrawi/Morphology/Disambiguator/DisambiguatorPrefixRule11.py
Sastrawi/Morphology/Disambiguator/DisambiguatorPrefixRule12.py
Sastrawi/Morphology/Disambiguator/DisambiguatorPrefixRule13.py
Sastrawi/Morphology/Disambiguator/DisambiguatorPrefixRule14.py
Sastrawi/Morphology/Disambiguator/DisambiguatorPrefixRule15.py
Sastrawi/Morphology/Disambiguator/DisambiguatorPrefixRule16.py
Sastrawi/Morphology/Disambiguator/DisambiguatorPrefixRule17.py
Sastrawi/Morphology/Disambiguator/DisambiguatorPrefixRule18.py
Sastrawi/Morphology/Disambiguator/DisambiguatorPrefixRule19.py
Sastrawi/Morphology/Disambiguator/DisambiguatorPrefixRule2.py
Sastrawi/Morphology/Disambiguator/DisambiguatorPrefixRule20.py
Sastrawi/Morphology/Disambiguator/DisambiguatorPrefixRule21.py
Sastrawi/Morphology/Disambiguator/DisambiguatorPrefixRule23.py
Sastrawi/Morphology/Disambiguator/DisambiguatorPrefixRule24.py
Sastrawi/Morphology/Disambiguator/DisambiguatorPrefixRule25.py
Sastrawi/Morphology/Disambiguator/DisambiguatorPrefixRule26.py
Sastrawi/Morphology/Disambiguator/DisambiguatorPrefixRule27.py
Sastrawi/Morphology/Disambiguator/DisambiguatorPrefixRule28.py
Sastrawi/Morphology/Disambiguator/DisambiguatorPrefixRule29.py
Sastrawi/Morphology/Disambiguator/DisambiguatorPrefixRule3.py
Sastrawi/Morphology/Disambiguator/DisambiguatorPrefixRule30.py
Sastrawi/Morphology/Disambiguator/DisambiguatorPrefixRule31.py
Sastrawi/Morphology/Disambiguator/DisambiguatorPrefixRule32.py
Sastrawi/Morphology/Disambiguator/DisambiguatorPrefixRule34.py
Sastrawi/Morphology/Disambiguator/DisambiguatorPrefixRule35.py
Sastrawi-1.0.1.dist-info/DESCRIPTION.rst
Sastrawi-1.0.1.dist-info/METADATA
Sastrawi-1.0.1.dist-info/RECORD
Sastrawi-1.0.1.dist-info/WHEEL
Sastrawi-1.0.1.dist-info/metadata.json
Sastrawi-1.0.1.dist-info/top_level.txt
